socialcrypt/__init__.py
socialcrypt-0.1.3.dist-info/METADATA
socialcrypt-0.1.3.dist-info/WHEEL
socialcrypt-0.1.3.dist-info/RECORD
