Metadata-Version: 2.1
Name: socialcrypt
Version: 0.1.3
Summary:  
Author: prathik shetty
Author-email: prathikkshetty15@gmail.com
Requires-Python: >=3.10,<4.0
Classifier: Programming Language :: Python :: 3
Classifier: Programming Language :: Python :: 3.10
Classifier: Programming Language :: Python :: 3.11
Classifier: Programming Language :: Python :: 3.12
Requires-Dist: Flask (==2.2.3)
Requires-Dist: Pillow (==9.5.0)
Requires-Dist: goose3 (==3.1.12)
Requires-Dist: matplotlib (==3.7.1)
Requires-Dist: numpy (>=1.23.2,<2.0.0)
Requires-Dist: pandas (==1.5.3)
Requires-Dist: plotly (==5.13.0)
Requires-Dist: python-dotenv (==1.0.0)
Requires-Dist: requests (==2.28.2)
Requires-Dist: snscrape (==0.6.2.20230320)
Requires-Dist: vaderSentiment (==3.3.2)
Requires-Dist: wordcloud (==1.8.2.2)
